chname/__init__.py
chname/__main__.py
chname-3.0.6.dist-info/METADATA
chname-3.0.6.dist-info/WHEEL
chname-3.0.6.dist-info/entry_points.txt
chname-3.0.6.dist-info/licenses/LICENSE
chname-3.0.6.dist-info/RECORD
