Metadata-Version: 2.4
Name: chname
Version: 3.0.6
Summary: Renames files in powerful ways
License-Expression: MIT
License-File: LICENSE
Keywords: rename,file,batch,bulk,utility,command-line,cli
Author: Steve Scholnick
Author-email: scholnicks@gmail.com
Requires-Python: >=3.13
Classifier: Development Status :: 5 - Production/Stable
Classifier: Intended Audience :: Developers
Classifier: Programming Language :: Python :: 3.13
Classifier: Programming Language :: Python :: 3.14
Classifier: License :: OSI Approved :: MIT License
Classifier: Topic :: Utilities
Requires-Dist: docopt-ng (>=0.9.0,<0.10.0)
Project-URL: Homepage, https://pypi.org/project/chname/
Project-URL: Issues, https://github.com/scholnicks/chname/issues
Project-URL: Repository, https://github.com/scholnicks/chname/
